chromwindow/__init__.py
chromwindow/chrom_sizes.py
chromwindow-1.1.5.dist-info/LICENSE
chromwindow-1.1.5.dist-info/METADATA
chromwindow-1.1.5.dist-info/WHEEL
chromwindow-1.1.5.dist-info/top_level.txt
chromwindow-1.1.5.dist-info/RECORD
