Metadata-Version: 2.1
Name: chromwindow
Version: 1.1.5
Summary: Utilities for working with windows on a chromosome.
Home-page: https://github.com/kaspermunch/chromwindow
Author: Kasper Munch
License: UNKNOWN
Platform: UNKNOWN
Requires-Python: >=3.6
Requires-Dist: pandas (>=1.0)
